<?xml version="1.0" encoding="UTF-8"?>
<Invoice>
  <InvoiceNumber>INV-2026075</InvoiceNumber>
  <InvoiceDate>2026-04-17</InvoiceDate>
  <Currency>USD</Currency>
  <VATRate>0.077</VATRate>
  <PaymentTerms>NET_30</PaymentTerms>
  <Vendor>
    <Name>Tech Solutions Inc.</Name>
    <TaxID>FR162911855</TaxID>
    <Country>United Kingdom</Country>
  </Vendor>
  <Buyer>
    <Name>Company-386 BV</Name>
    <Department>Sales</Department>
  </Buyer>
  <LineItems>
      <Item>
        <Description>Project Management</Description>
        <TaxCode>T03</TaxCode>
        <Quantity>70</Quantity>
        <Amount>278914.3</Amount>
      </Item>
      <Item>
        <Description>Network Equipment</Description>
        <TaxCode>H01</TaxCode>
        <Quantity>92</Quantity>
        <Amount>168139.2</Amount>
      </Item>
      <Item>
        <Description>Storage Array Expansion</Description>
        <TaxCode>H03</TaxCode>
        <Quantity>63</Quantity>
        <Amount>110437.11</Amount>
      </Item>
      <Item>
        <Description>Backup Solution</Description>
        <TaxCode>H04</TaxCode>
        <Quantity>65</Quantity>
        <Amount>106726.1</Amount>
      </Item>
      <Item>
        <Description>Data Analytics Platform</Description>
        <TaxCode>S05</TaxCode>
        <Quantity>24</Quantity>
        <Amount>4296.24</Amount>
      </Item>
      <Item>
        <Description>Backup Solution</Description>
        <TaxCode>H04</TaxCode>
        <Quantity>29</Quantity>
        <Amount>5656.45</Amount>
      </Item>
  </LineItems>
  <BankDetails>
    <IBAN>GB29NWBK60161331926819</IBAN>
    <BIC>NWBKGB2L</BIC>
  </BankDetails>
</Invoice>